care_survival/__init__.py
care_survival/aggregation.py
care_survival/care.py
care_survival/convex.py
care_survival/data.py
care_survival/distributions.py
care_survival/embedding.py
care_survival/kernel_estimator.py
care_survival/kernels.py
care_survival/metrics.py
care_survival/score2.py
care_survival-0.1.2.dist-info/METADATA
care_survival-0.1.2.dist-info/WHEEL
care_survival-0.1.2.dist-info/RECORD
