Metadata-Version: 2.4
Name: care-survival
Version: 0.1.2
Summary: Upgrading survival models with CARE
Requires-Python: >=3.10
Requires-Dist: matplotlib>=3.10.3
Requires-Dist: numpy
Requires-Dist: pandas
Requires-Dist: scipy>=1.15.3
